{
	"name": "Pip_Get_Meta_Data",
	"properties": {
		"activities": [
			{
				"name": "Metadata",
				"type": "GetMetadata",
				"dependsOn": [],
				"policy": {
					"timeout": "0.12:00:00",
					"retry": 0,
					"retryIntervalInSeconds": 30,
					"secureOutput": false,
					"secureInput": false
				},
				"userProperties": [],
				"typeProperties": {
					"dataset": {
						"referenceName": "DS_Get_Met_Data",
						"type": "DatasetReference"
					},
					"fieldList": [
						"childItems",
						"itemName",
						"itemType",
						"lastModified"
					],
					"storeSettings": {
						"type": "AzureBlobStorageReadSettings",
						"recursive": true,
						"enablePartitionDiscovery": false
					},
					"formatSettings": {
						"type": "DelimitedTextReadSettings"
					}
				}
			},
			{
				"name": "FilterFiles",
				"type": "Filter",
				"dependsOn": [
					{
						"activity": "Metadata",
						"dependencyConditions": [
							"Succeeded"
						]
					}
				],
				"userProperties": [],
				"typeProperties": {
					"items": {
						"value": "@activity('Metadata').output.childItems\n",
						"type": "Expression"
					},
					"condition": {
						"value": "@equals(item().type, 'File')\n",
						"type": "Expression"
					}
				}
			},
			{
				"name": "ForEachFile",
				"type": "ForEach",
				"dependsOn": [
					{
						"activity": "FilterFiles",
						"dependencyConditions": [
							"Completed"
						]
					}
				],
				"userProperties": [],
				"typeProperties": {
					"items": {
						"value": "@activity('FilterFiles').output.Value",
						"type": "Expression"
					},
					"activities": [
						{
							"name": "Switch1",
							"type": "Switch",
							"dependsOn": [],
							"userProperties": [],
							"typeProperties": {
								"on": {
									"value": "@last(split(item().name, '.'))",
									"type": "Expression"
								},
								"cases": [
									{
										"value": "csv",
										"activities": [
											{
												"name": "CSV_Copy",
												"type": "Copy",
												"dependsOn": [],
												"policy": {
													"timeout": "0.12:00:00",
													"retry": 0,
													"retryIntervalInSeconds": 30,
													"secureOutput": false,
													"secureInput": false
												},
												"userProperties": [],
												"typeProperties": {
													"source": {
														"type": "BinarySource",
														"storeSettings": {
															"type": "AzureBlobStorageReadSettings",
															"recursive": true
														},
														"formatSettings": {
															"type": "BinaryReadSettings"
														}
													},
													"sink": {
														"type": "BinarySink",
														"storeSettings": {
															"type": "AzureBlobFSWriteSettings"
														}
													},
													"enableStaging": false
												},
												"inputs": [
													{
														"referenceName": "DS_CSV_SOURCE",
														"type": "DatasetReference",
														"parameters": {
															"filename": {
																"value": "@item().name\n",
																"type": "Expression"
															}
														}
													}
												],
												"outputs": [
													{
														"referenceName": "DS_CSV_SINK",
														"type": "DatasetReference",
														"parameters": {
															"target_file": "@item().name"
														}
													}
												]
											}
										]
									},
									{
										"value": "txt",
										"activities": [
											{
												"name": "Copy_txt",
												"type": "Copy",
												"dependsOn": [],
												"policy": {
													"timeout": "0.12:00:00",
													"retry": 0,
													"retryIntervalInSeconds": 30,
													"secureOutput": false,
													"secureInput": false
												},
												"userProperties": [],
												"typeProperties": {
													"source": {
														"type": "BinarySource",
														"storeSettings": {
															"type": "AzureBlobStorageReadSettings",
															"recursive": true
														},
														"formatSettings": {
															"type": "BinaryReadSettings"
														}
													},
													"sink": {
														"type": "BinarySink",
														"storeSettings": {
															"type": "AzureBlobFSWriteSettings"
														}
													},
													"enableStaging": false
												},
												"inputs": [
													{
														"referenceName": "DS_TXT_SOURCE",
														"type": "DatasetReference",
														"parameters": {
															"filename": "@item().name"
														}
													}
												],
												"outputs": [
													{
														"referenceName": "DS_TXT_SINK",
														"type": "DatasetReference",
														"parameters": {
															"target_filename": "@item().name"
														}
													}
												]
											}
										]
									},
									{
										"value": "xlsx",
										"activities": [
											{
												"name": "Copy_xlsx",
												"type": "Copy",
												"dependsOn": [],
												"policy": {
													"timeout": "0.12:00:00",
													"retry": 0,
													"retryIntervalInSeconds": 30,
													"secureOutput": false,
													"secureInput": false
												},
												"userProperties": [],
												"typeProperties": {
													"source": {
														"type": "BinarySource",
														"storeSettings": {
															"type": "AzureBlobStorageReadSettings",
															"recursive": true
														},
														"formatSettings": {
															"type": "BinaryReadSettings"
														}
													},
													"sink": {
														"type": "BinarySink",
														"storeSettings": {
															"type": "AzureBlobFSWriteSettings"
														}
													},
													"enableStaging": false
												},
												"inputs": [
													{
														"referenceName": "DS_EXCEL_SOURCE",
														"type": "DatasetReference",
														"parameters": {
															"filename": {
																"value": "@item().name",
																"type": "Expression"
															}
														}
													}
												],
												"outputs": [
													{
														"referenceName": "DS_EXCEL_SINK",
														"type": "DatasetReference",
														"parameters": {
															"target_file": {
																"value": "@item().name",
																"type": "Expression"
															}
														}
													}
												]
											}
										]
									}
								]
							}
						}
					]
				}
			}
		],
		"annotations": [],
		"lastPublishTime": "2026-07-08T10:02:26Z"
	},
	"type": "Microsoft.DataFactory/factories/pipelines"
}